{"trial_id": "0004", "hyperparameters": {"space": [{"class_name": "Int", "config": {"name": "n_hidden", "default": 0, "conditions": [], "min_value": 0, "max_value": 8, "step": 1, "sampling": "linear"}}, {"class_name": "Float", "config": {"name": "learning_rate", "default": 0.0001, "conditions": [], "min_value": 0.0001, "max_value": 0.01, "step": null, "sampling": "log"}}, {"class_name": "Int", "config": {"name": "n_neurons", "default": null, "conditions": [], "min_value": 16, "max_value": 256, "step": 1, "sampling": "linear"}}, {"class_name": "Choice", "config": {"name": "optimizer", "default": "adam", "conditions": [], "values": ["adam", "sgd"], "ordered": false}}, {"class_name": "Boolean", "config": {"name": "normilize", "default": false, "conditions": []}}], "values": {"n_hidden": 0, "learning_rate": 0.00010234591515410909, "n_neurons": 172, "optimizer": "adam", "normilize": false, "tuner/epochs": 3, "tuner/initial_epoch": 0, "tuner/bracket": 1, "tuner/round": 0}}, "metrics": {"metrics": {"loss": {"direction": "min", "observations": [{"value": [10.054790496826172], "step": 2}]}, "accuracy": {"direction": "max", "observations": [{"value": [0.7607916593551636], "step": 2}]}, "val_loss": {"direction": "min", "observations": [{"value": [9.765049934387207], "step": 2}]}, "val_accuracy": {"direction": "max", "observations": [{"value": [0.765333354473114], "step": 2}]}}}, "score": 0.765333354473114, "best_step": 2, "status": "COMPLETED", "message": null}